<annotation>
	<folder>data</folder>
	<filename>000361.jpg</filename>
	<path>/Users/liubeiming/Desktop/口罩数据集/刘倍铭/data/000361.jpg</path>
	<source>
		<database>Unknown</database>
	</source>
	<size>
		<width>600</width>
		<height>367</height>
		<depth>3</depth>
	</size>
	<segmented>0</segmented>
	<object>
		<name>nomask</name>
		<pose>Unspecified</pose>
		<truncated>0</truncated>
		<difficult>0</difficult>
		<bndbox>
			<xmin>59</xmin>
			<ymin>148</ymin>
			<xmax>156</xmax>
			<ymax>277</ymax>
		</bndbox>
	</object>
	<object>
		<name>nomask</name>
		<pose>Unspecified</pose>
		<truncated>0</truncated>
		<difficult>0</difficult>
		<bndbox>
			<xmin>290</xmin>
			<ymin>34</ymin>
			<xmax>366</xmax>
			<ymax>136</ymax>
		</bndbox>
	</object>
	<object>
		<name>nomask</name>
		<pose>Unspecified</pose>
		<truncated>0</truncated>
		<difficult>0</difficult>
		<bndbox>
			<xmin>406</xmin>
			<ymin>169</ymin>
			<xmax>487</xmax>
			<ymax>291</ymax>
		</bndbox>
	</object>
	<object>
		<name>nomask</name>
		<pose>Unspecified</pose>
		<truncated>0</truncated>
		<difficult>0</difficult>
		<bndbox>
			<xmin>367</xmin>
			<ymin>50</ymin>
			<xmax>450</xmax>
			<ymax>189</ymax>
		</bndbox>
	</object>
</annotation>
