<annotation>
	<folder>data</folder>
	<filename>001357.jpg</filename>
	<path>/Users/liubeiming/Desktop/口罩数据集/刘倍铭/part2/data/001357.jpg</path>
	<source>
		<database>Unknown</database>
	</source>
	<size>
		<width>550</width>
		<height>362</height>
		<depth>3</depth>
	</size>
	<segmented>0</segmented>
	<object>
		<name>nomask</name>
		<pose>Unspecified</pose>
		<truncated>0</truncated>
		<difficult>0</difficult>
		<bndbox>
			<xmin>219</xmin>
			<ymin>79</ymin>
			<xmax>247</xmax>
			<ymax>130</ymax>
		</bndbox>
	</object>
	<object>
		<name>nomask</name>
		<pose>Unspecified</pose>
		<truncated>0</truncated>
		<difficult>0</difficult>
		<bndbox>
			<xmin>244</xmin>
			<ymin>121</ymin>
			<xmax>303</xmax>
			<ymax>198</ymax>
		</bndbox>
	</object>
	<object>
		<name>nomask</name>
		<pose>Unspecified</pose>
		<truncated>0</truncated>
		<difficult>0</difficult>
		<bndbox>
			<xmin>326</xmin>
			<ymin>103</ymin>
			<xmax>353</xmax>
			<ymax>150</ymax>
		</bndbox>
	</object>
	<object>
		<name>nomask</name>
		<pose>Unspecified</pose>
		<truncated>0</truncated>
		<difficult>0</difficult>
		<bndbox>
			<xmin>372</xmin>
			<ymin>118</ymin>
			<xmax>413</xmax>
			<ymax>177</ymax>
		</bndbox>
	</object>
	<object>
		<name>nomask</name>
		<pose>Unspecified</pose>
		<truncated>0</truncated>
		<difficult>0</difficult>
		<bndbox>
			<xmin>391</xmin>
			<ymin>140</ymin>
			<xmax>453</xmax>
			<ymax>224</ymax>
		</bndbox>
	</object>
	<object>
		<name>nomask</name>
		<pose>Unspecified</pose>
		<truncated>0</truncated>
		<difficult>0</difficult>
		<bndbox>
			<xmin>393</xmin>
			<ymin>200</ymin>
			<xmax>472</xmax>
			<ymax>323</ymax>
		</bndbox>
	</object>
	<object>
		<name>nomask</name>
		<pose>Unspecified</pose>
		<truncated>0</truncated>
		<difficult>0</difficult>
		<bndbox>
			<xmin>442</xmin>
			<ymin>88</ymin>
			<xmax>475</xmax>
			<ymax>145</ymax>
		</bndbox>
	</object>
</annotation>
