<annotation>
	<folder>data</folder>
	<filename>part2_000094.jpg</filename>
	<path>/Users/liubeiming/Desktop/口罩数据集/刘倍铭/part2/data/part2_000094.jpg</path>
	<source>
		<database>Unknown</database>
	</source>
	<size>
		<width>250</width>
		<height>275</height>
		<depth>3</depth>
	</size>
	<segmented>0</segmented>
	<object>
		<name>nomask</name>
		<pose>Unspecified</pose>
		<truncated>0</truncated>
		<difficult>0</difficult>
		<bndbox>
			<xmin>102</xmin>
			<ymin>37</ymin>
			<xmax>165</xmax>
			<ymax>124</ymax>
		</bndbox>
	</object>
</annotation>
