<annotation>
	<folder>part2</folder>
	<filename>part2_000597.jpg</filename>
	<path>G:\疫情期间\AI\数据标注\part2\part2\part2_000597.jpg</path>
	<source>
		<database>Unknown</database>
	</source>
	<size>
		<width>919</width>
		<height>765</height>
		<depth>3</depth>
	</size>
	<segmented>0</segmented>
	<object>
		<name>nomask</name>
		<pose>Unspecified</pose>
		<truncated>0</truncated>
		<difficult>0</difficult>
		<bndbox>
			<xmin>574</xmin>
			<ymin>307</ymin>
			<xmax>721</xmax>
			<ymax>437</ymax>
		</bndbox>
	</object>
	<object>
		<name>nomask</name>
		<pose>Unspecified</pose>
		<truncated>0</truncated>
		<difficult>0</difficult>
		<bndbox>
			<xmin>124</xmin>
			<ymin>183</ymin>
			<xmax>310</xmax>
			<ymax>289</ymax>
		</bndbox>
	</object>
</annotation>
