<annotation>
	<folder>yuantu</folder>
	<filename>part2_002277.jpg</filename>
	<path>D:\11111\part2-lrh\yuantu\part2_002277.jpg</path>
	<source>
		<database>Unknown</database>
	</source>
	<size>
		<width>3648</width>
		<height>3648</height>
		<depth>3</depth>
	</size>
	<segmented>0</segmented>
	<object>
		<name>nomask</name>
		<pose>Unspecified</pose>
		<truncated>1</truncated>
		<difficult>0</difficult>
		<bndbox>
			<xmin>491</xmin>
			<ymin>2255</ymin>
			<xmax>3197</xmax>
			<ymax>3648</ymax>
		</bndbox>
	</object>
</annotation>
