<annotation>
	<folder>yuantu</folder>
	<filename>part2_001660.jpg</filename>
	<path>D:\11111\part2-lrh\yuantu\part2_001660.jpg</path>
	<source>
		<database>Unknown</database>
	</source>
	<size>
		<width>2592</width>
		<height>1728</height>
		<depth>3</depth>
	</size>
	<segmented>0</segmented>
	<object>
		<name>nomask</name>
		<pose>Unspecified</pose>
		<truncated>0</truncated>
		<difficult>0</difficult>
		<bndbox>
			<xmin>626</xmin>
			<ymin>463</ymin>
			<xmax>878</xmax>
			<ymax>760</ymax>
		</bndbox>
	</object>
	<object>
		<name>nomask</name>
		<pose>Unspecified</pose>
		<truncated>0</truncated>
		<difficult>0</difficult>
		<bndbox>
			<xmin>1332</xmin>
			<ymin>454</ymin>
			<xmax>1580</xmax>
			<ymax>738</ymax>
		</bndbox>
	</object>
	<object>
		<name>nomask</name>
		<pose>Unspecified</pose>
		<truncated>0</truncated>
		<difficult>0</difficult>
		<bndbox>
			<xmin>1991</xmin>
			<ymin>400</ymin>
			<xmax>2251</xmax>
			<ymax>714</ymax>
		</bndbox>
	</object>
</annotation>
