<annotation>
	<folder>part2</folder>
	<filename>part2_001419.jpg</filename>
	<path>G:\疫情期间\AI\数据标注\part2\part2\part2_001419.jpg</path>
	<source>
		<database>Unknown</database>
	</source>
	<size>
		<width>430</width>
		<height>265</height>
		<depth>3</depth>
	</size>
	<segmented>0</segmented>
	<object>
		<name>nomask</name>
		<pose>Unspecified</pose>
		<truncated>0</truncated>
		<difficult>0</difficult>
		<bndbox>
			<xmin>102</xmin>
			<ymin>14</ymin>
			<xmax>182</xmax>
			<ymax>67</ymax>
		</bndbox>
	</object>
	<object>
		<name>nomask</name>
		<pose>Unspecified</pose>
		<truncated>0</truncated>
		<difficult>0</difficult>
		<bndbox>
			<xmin>285</xmin>
			<ymin>14</ymin>
			<xmax>382</xmax>
			<ymax>106</ymax>
		</bndbox>
	</object>
</annotation>
