<annotation>
	<folder>data</folder>
	<filename>part2_000176.jpg</filename>
	<path>/Users/liubeiming/Desktop/口罩数据集/刘倍铭/part2/data/part2_000176.jpg</path>
	<source>
		<database>Unknown</database>
	</source>
	<size>
		<width>780</width>
		<height>439</height>
		<depth>3</depth>
	</size>
	<segmented>0</segmented>
	<object>
		<name>nomask</name>
		<pose>Unspecified</pose>
		<truncated>0</truncated>
		<difficult>0</difficult>
		<bndbox>
			<xmin>156</xmin>
			<ymin>95</ymin>
			<xmax>267</xmax>
			<ymax>251</ymax>
		</bndbox>
	</object>
</annotation>
